WSME-0.12.1-py3.11-nspkg.pth
wsme/__init__.py
wsme/api.py
wsme/exc.py
wsme/protocol.py
wsme/root.py
wsme/runtime.py
wsme/types.py
wsme/utils.py
wsme/rest/__init__.py
wsme/rest/args.py
wsme/rest/json.py
wsme/rest/protocol.py
wsme/rest/xml.py
wsme/tests/__init__.py
wsme/tests/protocol.py
wsme/tests/test_api.py
wsme/tests/test_exc.py
wsme/tests/test_protocols.py
wsme/tests/test_protocols_commons.py
wsme/tests/test_restjson.py
wsme/tests/test_restxml.py
wsme/tests/test_root.py
wsme/tests/test_types.py
wsme/tests/test_utils.py
wsmeext/flask.py
wsmeext/pecan.py
wsmeext/sphinxext.py
WSME-0.12.1.dist-info/AUTHORS
WSME-0.12.1.dist-info/LICENSE
WSME-0.12.1.dist-info/METADATA
WSME-0.12.1.dist-info/WHEEL
WSME-0.12.1.dist-info/entry_points.txt
WSME-0.12.1.dist-info/namespace_packages.txt
WSME-0.12.1.dist-info/pbr.json
WSME-0.12.1.dist-info/top_level.txt
WSME-0.12.1.dist-info/RECORD
