Metadata-Version: 2.1
Name: WSME
Version: 0.12.1
Summary: Simplify the writing of REST APIs, and extend them with additional protocols.
Home-page: https://opendev.org/x/wsme
Author: Christophe de Vienne
Author-email: python-wsme@googlegroups.com
License: MIT
Classifier: Development Status :: 3 - Alpha
Classifier: Operating System :: OS Independent
Classifier: Programming Language :: Python
Classifier: Programming Language :: Python :: 3
Classifier: Programming Language :: Python :: 3 :: Only
Classifier: License :: OSI Approved :: MIT License
Classifier: Topic :: Internet :: WWW/HTTP :: WSGI
Classifier: Topic :: Software Development :: Libraries :: Python Modules
Requires-Python: >=3.8
License-File: LICENSE
License-File: AUTHORS
Requires-Dist: WebOb>=1.8.0
Requires-Dist: simplegeneric
Requires-Dist: pytz
Requires-Dist: netaddr>=0.7.12
Requires-Dist: importlib_metadata>=4.4
